jaxert/__init__.py
jaxert/core.py
jaxert/version.py
jaxert-1.0.0.dist-info/METADATA
jaxert-1.0.0.dist-info/WHEEL
jaxert-1.0.0.dist-info/licenses/LICENSE
jaxert-1.0.0.dist-info/RECORD
