Metadata-Version: 2.3
Name: jaxert
Version: 1.0.0
Project-URL: Source Code, https://github.com/ymd-h/jaxert
License: MIT License
License-File: LICENSE
Classifier: Topic :: Software Development :: Testing
Requires-Python: >=3.8
Requires-Dist: jax
